RobloxPyApi3Update/__init__.py
RobloxPyApi3Update-1.0.1.dist-info/METADATA
RobloxPyApi3Update-1.0.1.dist-info/WHEEL
RobloxPyApi3Update-1.0.1.dist-info/top_level.txt
RobloxPyApi3Update-1.0.1.dist-info/RECORD
