Metadata-Version: 2.1
Name: RobloxPyApi3Update
Version: 1.0.1
Summary: A package allows you to update RobloxPyApi3 Package
Home-page: UNKNOWN
Author: pyProjects3 (github.com/pyProjects3)
License: UNKNOWN
Keywords: RobloxPyApi3,UnInstall,CheckforVersion,Upgrade,Pip,Install
Platform: UNKNOWN
Classifier: Development Status :: 1 - Planning
Classifier: Intended Audience :: Developers
Classifier: Programming Language :: Python :: 3
Classifier: Operating System :: Microsoft :: Windows
Requires-Dist: requests
